[
 {
  "tcId": "FCB-6875",
  "summary": "TradeFinance_Export_Bills_Under_Collection_Realize_Lodge_Sight_Foreign_EUR_ByMaker_M7",
  "username": "PT19",
  "password": "Infy@123",
  "menu": "PEOBR",
  "ccy": "EUR",
  "billId": "'1401EDC24000088",
  "realizationAccountId": "'1001003104010011",
  "billRealizationAmount": 1,
  "realizationValueDate": "'13-11-2023",
  "mixedBill1RealizationAccountId": "'1001003104010011",
  "mixedBill2RealizationAccountId": "'1001003104010011",
  "expectedResult": "successfully",
  "linkedTcid": "FCB-6876"
 },
 {
  "tcId": "FCB-6855",
  "summary": "TradeFinance_Export_Bills_Under_Collection_Realize_Lodge_Mixed Tenor_Local_EGP_ByMaker_H5",
  "username": "PT19",
  "password": "Infy@123",
  "menu": "PEOBR",
  "ccy": "EGP",
  "billId": "'1401EDC24000089",
  "mixedBillId1": "'1401EDC24000090",
  "mixedBillId2": "'1401EDC24000091",
  "realizationAccountId": "'1001001104010013",
  "mixedBill1RealizationAccountId": "'1001001104010013",
  "mixedBill1RealizationAmount": 1,
  "mixedBill1RealizationValueDate": "'13-11-2023",
  "mixedBill2RealizationAccountId": "'1001001104010013",
  "mixedBill2RealizationAmount": 1,
  "mixedBill2RealizationValueDate": "'13-11-2023",
  "expectedResult": "successfully",
  "linkedTcid": "FCB-6856"
 },
 {
  "tcId": "FCB-6807",
  "summary": "TradeFinance_Export_Bills_Under_Collection_Realize_Lodge_Usance_Local_EGP_ByMaker_C7",
  "username": "PT19",
  "password": "Infy@123",
  "menu": "PEOBR",
  "ccy": "EGP",
  "billId": "'1401EDC24000092",
  "realizationAccountId": "'1001001102010002",
  "billRealizationAmount": 1,
  "realizationValueDate": "'13-11-2023",
  "mixedBill1RealizationAccountId": "'1001001102010002",
  "mixedBill2RealizationAccountId": "'1001001102010002",
  "expectedResult": "successfully",
  "linkedTcid": "FCB-6808"
 },
 {
  "tcId": "FCB-6827",
  "summary": "TradeFinance_Export_Bills_Under_Collection_Realize_Lodge_Usance_Foreign_EUR_ByMaker_E9",
  "username": "PT19",
  "password": "Infy@123",
  "menu": "PEOBR",
  "ccy": "EUR",
  "billId": "'1401EDC24000094",
  "realizationAccountId": "'1001003104010011",
  "billRealizationAmount": 1,
  "realizationValueDate": "'13-11-2023",
  "mixedBill1RealizationAccountId": "'1001003104010011",
  "mixedBill2RealizationAccountId": "'1001003104010011",
  "expectedResult": "successfully",
  "linkedTcid": "FCB-6828"
 },
 {
  "tcId": "FCB-6835",
  "summary": "TradeFinance_Export_Bills_Under_Collection_Partial_Realize_Lodge_Mixed Tenor_Foreign_USD_ByMaker_F7",
  "username": "PT19",
  "password": "Infy@123",
  "menu": "PEOBR",
  "ccy": "USD",
  "billId": "'1401EDC24000095",
  "mixedBillId1": "'1401EDC24000096",
  "mixedBillId2": "'1401EDC24000097",
  "realizationAccountId": "'1001002104010013",
  "mixedBill1RealizationAccountId": "'1001002104010013",
  "mixedBill1RealizationAmount": 1,
  "mixedBill1RealizationValueDate": "'13-11-2023",
  "mixedBill2RealizationAccountId": "'1001002104010013",
  "mixedBill2RealizationAmount": 1,
  "mixedBill2RealizationValueDate": "'13-11-2023",
  "expectedResult": "successfully",
  "linkedTcid": "FCB-6836"
 },
 {
  "tcId": "FCB-7180",
  "summary": "TradeFinance_Export_Bills_Under_Documentary_Credit_Realize_Lodge_Usance_Local_EGP_ByMaker_A7",
  "username": "PT19",
  "password": "Infy@123",
  "menu": "PEOBR",
  "ccy": "EGP",
  "realizationAccountId": "'1001001102010002",
  "billRealizationAmount": 1,
  "realizationValueDate": "'13-11-2023",
  "mixedBill1RealizationAccountId": "'1001001102010002",
  "mixedBill2RealizationAccountId": "'1001001102010002",
  "expectedResult": "successfully",
  "linkedTcid": "FCB-7181"
 },
 {
  "tcId": "FCB-7202",
  "summary": "TradeFinance_Export_Bills_Under_Documentary_Credit_Realize_Lodge_Sight_Foriegn_EUR_ByMaker_D3",
  "username": "PT19",
  "password": "Infy@123",
  "menu": "PEOBR",
  "ccy": "EUR",
  "billId": "'1401EDC24000098",
  "realizationAccountId": "'1001003102010001",
  "billRealizationAmount": 1,
  "realizationValueDate": "'13-11-2023",
  "mixedBill1RealizationAccountId": "'1001003102010001",
  "mixedBill2RealizationAccountId": "'1001003102010001",
  "expectedResult": "successfully",
  "linkedTcid": "FCB-7203"
 },
 {
  "tcId": "FCB-7236",
  "summary": "TradeFinance_Export_Bills_Under_Documentary_Credit_Realize_Lodge_Mixed Tenor_Foreign_USD_ByMaker_J9",
  "username": "PT19",
  "password": "Infy@123",
  "menu": "PEOBR",
  "ccy": "USD",
  "billId": "'1401EDC24000100",
  "mixedBillId1": "'1401EDC24000101",
  "mixedBillId2": "'1401EDC24000102",
  "realizationAccountId": "'1001002104010013",
  "mixedBill1RealizationAccountId": "'1001002104010013",
  "mixedBill1RealizationAmount": 1,
  "mixedBill1RealizationValueDate": "'13-11-2023",
  "mixedBill2RealizationAccountId": "'1001002104010013",
  "mixedBill2RealizationAmount": 1,
  "mixedBill2RealizationValueDate": "'13-11-2023",
  "expectedResult": "successfully",
  "linkedTcid": "FCB-7237"
 }
]